[
    {
        "date": "2024-05-27",
        "river_flow": 1232,
        "water_level": 2.91,
        "water_temperature": 57
    },
    {
        "date": "2024-05-28",
        "river_flow": 874,
        "water_level": 3.36,
        "water_temperature": 56
    },
    {
        "date": "2024-05-29",
        "river_flow": 1886,
        "water_level": 3.38,
        "water_temperature": 64
    },
    {
        "date": "2024-05-30",
        "river_flow": 1026,
        "water_level": 4.28,
        "water_temperature": 74
    },
    {
        "date": "2024-05-31",
        "river_flow": 854,
        "water_level": 2.92,
        "water_temperature": 74
    },
    {
        "date": "2024-06-01",
        "river_flow": 1251,
        "water_level": 3.63,
        "water_temperature": 72
    },
    {
        "date": "2024-06-02",
        "river_flow": 1202,
        "water_level": 3.97,
        "water_temperature": 65
    },
    {
        "date": "2024-06-03",
        "river_flow": 1682,
        "water_level": 2.64,
        "water_temperature": 73
    },
    {
        "date": "2024-06-04",
        "river_flow": 818,
        "water_level": 4.25,
        "water_temperature": 58
    },
    {
        "date": "2024-06-05",
        "river_flow": 1718,
        "water_level": 3.06,
        "water_temperature": 66
    },
    {
        "date": "2024-06-06",
        "river_flow": 1337,
        "water_level": 3.8,
        "water_temperature": 62
    },
    {
        "date": "2024-06-07",
        "river_flow": 831,
        "water_level": 3.35,
        "water_temperature": 66
    },
    {
        "date": "2024-06-08",
        "river_flow": 881,
        "water_level": 4.44,
        "water_temperature": 70
    },
    {
        "date": "2024-06-09",
        "river_flow": 1633,
        "water_level": 2.87,
        "water_temperature": 68
    },
    {
        "date": "2024-06-10",
        "river_flow": 1404,
        "water_level": 3.45,
        "water_temperature": 67
    },
    {
        "date": "2024-06-11",
        "river_flow": 1388,
        "water_level": 2.9,
        "water_temperature": 70
    },
    {
        "date": "2024-06-12",
        "river_flow": 1805,
        "water_level": 2.76,
        "water_temperature": 61
    },
    {
        "date": "2024-06-13",
        "river_flow": 1044,
        "water_level": 3.43,
        "water_temperature": 58
    },
    {
        "date": "2024-06-14",
        "river_flow": 1254,
        "water_level": 4.84,
        "water_temperature": 63
    },
    {
        "date": "2024-06-15",
        "river_flow": 1982,
        "water_level": 4.53,
        "water_temperature": 73
    },
    {
        "date": "2024-06-16",
        "river_flow": 877,
        "water_level": 3.79,
        "water_temperature": 74
    },
    {
        "date": "2024-06-17",
        "river_flow": 1850,
        "water_level": 3.4,
        "water_temperature": 66
    },
    {
        "date": "2024-06-18",
        "river_flow": 803,
        "water_level": 2.83,
        "water_temperature": 66
    },
    {
        "date": "2024-06-19",
        "river_flow": 823,
        "water_level": 4.5,
        "water_temperature": 66
    },
    {
        "date": "2024-06-20",
        "river_flow": 1345,
        "water_level": 3.53,
        "water_temperature": 69
    },
    {
        "date": "2024-06-21",
        "river_flow": 1603,
        "water_level": 2.5,
        "water_temperature": 58
    },
    {
        "date": "2024-06-22",
        "river_flow": 944,
        "water_level": 4.77,
        "water_temperature": 65
    },
    {
        "date": "2024-06-23",
        "river_flow": 810,
        "water_level": 4.82,
        "water_temperature": 55
    },
    {
        "date": "2024-06-24",
        "river_flow": 1339,
        "water_level": 4.84,
        "water_temperature": 71
    },
    {
        "date": "2024-06-25",
        "river_flow": 1488,
        "water_level": 4.77,
        "water_temperature": 71
    },
    {
        "date": "2024-06-26",
        "river_flow": 1372,
        "water_level": 3.71,
        "water_temperature": 61
    },
    {
        "date": "2024-06-27",
        "river_flow": 1691,
        "water_level": 4.46,
        "water_temperature": 72
    },
    {
        "date": "2024-06-28",
        "river_flow": 1266,
        "water_level": 4.26,
        "water_temperature": 73
    },
    {
        "date": "2024-06-29",
        "river_flow": 912,
        "water_level": 3.51,
        "water_temperature": 65
    },
    {
        "date": "2024-06-30",
        "river_flow": 1303,
        "water_level": 2.81,
        "water_temperature": 56
    },
    {
        "date": "2024-07-01",
        "river_flow": 1801,
        "water_level": 3.06,
        "water_temperature": 66
    },
    {
        "date": "2024-07-02",
        "river_flow": 912,
        "water_level": 3.07,
        "water_temperature": 66
    },
    {
        "date": "2024-07-03",
        "river_flow": 1800,
        "water_level": 3.44,
        "water_temperature": 72
    },
    {
        "date": "2024-07-04",
        "river_flow": 1071,
        "water_level": 3.85,
        "water_temperature": 73
    },
    {
        "date": "2024-07-05",
        "river_flow": 1021,
        "water_level": 3.31,
        "water_temperature": 62
    },
    {
        "date": "2024-07-06",
        "river_flow": 1227,
        "water_level": 3.36,
        "water_temperature": 67
    },
    {
        "date": "2024-07-07",
        "river_flow": 1470,
        "water_level": 3.57,
        "water_temperature": 64
    },
    {
        "date": "2024-07-08",
        "river_flow": 1255,
        "water_level": 4.48,
        "water_temperature": 69
    },
    {
        "date": "2024-07-09",
        "river_flow": 1586,
        "water_level": 4.72,
        "water_temperature": 71
    },
    {
        "date": "2024-07-10",
        "river_flow": 1275,
        "water_level": 4.47,
        "water_temperature": 73
    },
    {
        "date": "2024-07-11",
        "river_flow": 813,
        "water_level": 2.62,
        "water_temperature": 55
    },
    {
        "date": "2024-07-12",
        "river_flow": 1552,
        "water_level": 3.73,
        "water_temperature": 55
    },
    {
        "date": "2024-07-13",
        "river_flow": 905,
        "water_level": 4.27,
        "water_temperature": 72
    },
    {
        "date": "2024-07-14",
        "river_flow": 1236,
        "water_level": 2.81,
        "water_temperature": 58
    },
    {
        "date": "2024-07-15",
        "river_flow": 1319,
        "water_level": 4.85,
        "water_temperature": 61
    },
    {
        "date": "2024-07-16",
        "river_flow": 1697,
        "water_level": 3.38,
        "water_temperature": 58
    },
    {
        "date": "2024-07-17",
        "river_flow": 1222,
        "water_level": 3.25,
        "water_temperature": 56
    },
    {
        "date": "2024-07-18",
        "river_flow": 1951,
        "water_level": 4.66,
        "water_temperature": 69
    },
    {
        "date": "2024-07-19",
        "river_flow": 1724,
        "water_level": 3.74,
        "water_temperature": 71
    },
    {
        "date": "2024-07-20",
        "river_flow": 1468,
        "water_level": 4.52,
        "water_temperature": 60
    },
    {
        "date": "2024-07-21",
        "river_flow": 1156,
        "water_level": 3.9,
        "water_temperature": 63
    },
    {
        "date": "2024-07-22",
        "river_flow": 848,
        "water_level": 3.85,
        "water_temperature": 64
    },
    {
        "date": "2024-07-23",
        "river_flow": 1108,
        "water_level": 4.9,
        "water_temperature": 59
    },
    {
        "date": "2024-07-24",
        "river_flow": 993,
        "water_level": 3.78,
        "water_temperature": 61
    },
    {
        "date": "2024-07-25",
        "river_flow": 1770,
        "water_level": 4.6,
        "water_temperature": 70
    },
    {
        "date": "2024-07-26",
        "river_flow": 1388,
        "water_level": 3.78,
        "water_temperature": 58
    },
    {
        "date": "2024-07-27",
        "river_flow": 1782,
        "water_level": 2.78,
        "water_temperature": 59
    },
    {
        "date": "2024-07-28",
        "river_flow": 1947,
        "water_level": 3.67,
        "water_temperature": 73
    },
    {
        "date": "2024-07-29",
        "river_flow": 1580,
        "water_level": 2.59,
        "water_temperature": 69
    },
    {
        "date": "2024-07-30",
        "river_flow": 1629,
        "water_level": 2.57,
        "water_temperature": 66
    },
    {
        "date": "2024-07-31",
        "river_flow": 1121,
        "water_level": 3.49,
        "water_temperature": 71
    },
    {
        "date": "2024-08-01",
        "river_flow": 1428,
        "water_level": 2.96,
        "water_temperature": 58
    },
    {
        "date": "2024-08-02",
        "river_flow": 898,
        "water_level": 3.79,
        "water_temperature": 60
    },
    {
        "date": "2024-08-03",
        "river_flow": 1410,
        "water_level": 3.96,
        "water_temperature": 66
    },
    {
        "date": "2024-08-04",
        "river_flow": 1514,
        "water_level": 4.11,
        "water_temperature": 62
    },
    {
        "date": "2024-08-05",
        "river_flow": 1514,
        "water_level": 3.14,
        "water_temperature": 62
    },
    {
        "date": "2024-08-06",
        "river_flow": 1185,
        "water_level": 3.53,
        "water_temperature": 73
    },
    {
        "date": "2024-08-07",
        "river_flow": 1565,
        "water_level": 4.57,
        "water_temperature": 56
    },
    {
        "date": "2024-08-08",
        "river_flow": 1941,
        "water_level": 4.81,
        "water_temperature": 61
    },
    {
        "date": "2024-08-09",
        "river_flow": 1395,
        "water_level": 3.84,
        "water_temperature": 55
    },
    {
        "date": "2024-08-10",
        "river_flow": 1456,
        "water_level": 4.7,
        "water_temperature": 73
    },
    {
        "date": "2024-08-11",
        "river_flow": 1498,
        "water_level": 3.0,
        "water_temperature": 74
    },
    {
        "date": "2024-08-12",
        "river_flow": 1029,
        "water_level": 4.95,
        "water_temperature": 71
    },
    {
        "date": "2024-08-13",
        "river_flow": 1780,
        "water_level": 4.85,
        "water_temperature": 75
    },
    {
        "date": "2024-08-14",
        "river_flow": 1035,
        "water_level": 4.04,
        "water_temperature": 64
    },
    {
        "date": "2024-08-15",
        "river_flow": 1260,
        "water_level": 3.27,
        "water_temperature": 75
    },
    {
        "date": "2024-08-16",
        "river_flow": 1639,
        "water_level": 4.36,
        "water_temperature": 58
    },
    {
        "date": "2024-08-17",
        "river_flow": 996,
        "water_level": 4.91,
        "water_temperature": 59
    },
    {
        "date": "2024-08-18",
        "river_flow": 1533,
        "water_level": 4.37,
        "water_temperature": 55
    },
    {
        "date": "2024-08-19",
        "river_flow": 845,
        "water_level": 3.57,
        "water_temperature": 64
    },
    {
        "date": "2024-08-20",
        "river_flow": 1135,
        "water_level": 4.23,
        "water_temperature": 72
    },
    {
        "date": "2024-08-21",
        "river_flow": 1021,
        "water_level": 3.46,
        "water_temperature": 58
    },
    {
        "date": "2024-08-22",
        "river_flow": 1156,
        "water_level": 3.16,
        "water_temperature": 70
    },
    {
        "date": "2024-08-23",
        "river_flow": 1297,
        "water_level": 3.44,
        "water_temperature": 56
    },
    {
        "date": "2024-08-24",
        "river_flow": 1286,
        "water_level": 3.24,
        "water_temperature": 69
    },
    {
        "date": "2024-08-25",
        "river_flow": 1262,
        "water_level": 4.63,
        "water_temperature": 55
    },
    {
        "date": "2024-08-26",
        "river_flow": 1216,
        "water_level": 4.98,
        "water_temperature": 71
    },
    {
        "date": "2024-08-27",
        "river_flow": 1480,
        "water_level": 4.35,
        "water_temperature": 57
    },
    {
        "date": "2024-08-28",
        "river_flow": 1449,
        "water_level": 4.18,
        "water_temperature": 61
    },
    {
        "date": "2024-08-29",
        "river_flow": 1571,
        "water_level": 3.27,
        "water_temperature": 56
    },
    {
        "date": "2024-08-30",
        "river_flow": 1700,
        "water_level": 3.07,
        "water_temperature": 57
    },
    {
        "date": "2024-08-31",
        "river_flow": 1788,
        "water_level": 3.95,
        "water_temperature": 65
    },
    {
        "date": "2024-09-01",
        "river_flow": 1571,
        "water_level": 2.55,
        "water_temperature": 65
    },
    {
        "date": "2024-09-02",
        "river_flow": 1524,
        "water_level": 4.3,
        "water_temperature": 58
    }
]